aqsc/__init__.py
aqsc/aqsc_to_desc.py
aqsc/chiphiepsfunc.py
aqsc/chiphifunc.py
aqsc/chiphifunc_test_suite.py
aqsc/config.py
aqsc/equilibrium.py
aqsc/leading_orders.py
aqsc/looped_solver.py
aqsc/math_utilities.py
aqsc/recursion_relations.py
aqsc/unsupported_by_jax.py
aqsc/MHD_parsed/__init__.py
aqsc/MHD_parsed/eval_D3_RHS_m_LHS.py
aqsc/MHD_parsed/eval_Delta_n.py
aqsc/MHD_parsed/eval_II_center.py
aqsc/MHD_parsed/eval_loop.py
aqsc/MHD_parsed/eval_p_perp_n.py
aqsc/MHD_parsed/validate.py
aqsc/looped_coefs/B_psi_coefs_in_D3.py
aqsc/looped_coefs/Y_coefs.py
aqsc/looped_coefs/Y_coefs_in_D3.py
aqsc/looped_coefs/__init__.py
aqsc/looped_coefs/bkup.py
aqsc/looped_coefs/direct_B_theta_coefs.py
aqsc/looped_coefs/lambda_B_psi_coef.py
aqsc/looped_coefs/lambda_B_psi_coef_in_vars.py
aqsc/parsed/__init__.py
aqsc/parsed/eval_D3_RHS_m_LHS.py
aqsc/parsed/eval_Xn.py
aqsc/parsed/eval_Ynp1.py
aqsc/parsed/eval_Znp1.py
aqsc/parsed/eval_dchi_B_psi_nm2.py
aqsc-0.1.10.dist-info/LICENSE
aqsc-0.1.10.dist-info/METADATA
aqsc-0.1.10.dist-info/WHEEL
aqsc-0.1.10.dist-info/top_level.txt
aqsc-0.1.10.dist-info/RECORD
