Metadata-Version: 2.1
Name: aqsc
Version: 0.1.10
Summary: Constructs QS stellarator equilibrium to all orders.
Author-email: Lanke Fu <ffu@pppl.gov>
Project-URL: Homepage, https://github.com/lankef/pyAQSC
License-File: LICENSE
Requires-Dist: numpy
Requires-Dist: matplotlib
Requires-Dist: jax
Requires-Dist: scipy
